packageamey/__init__.py
packageamey-0.3.dist-info/License.txt
packageamey-0.3.dist-info/METADATA
packageamey-0.3.dist-info/WHEEL
packageamey-0.3.dist-info/top_level.txt
packageamey-0.3.dist-info/RECORD
