Metadata-Version: 2.1
Name: packageamey
Version: 0.3
Summary: This is cool
Home-page: UNKNOWN
Author: Amey
Author-email: UNKNOWN
License: UNKNOWN
Platform: UNKNOWN
